pytsql/__init__.py
pytsql/__main__.py
pytsql/tsql.py
pytsql/grammar/TSqlLexer.g4
pytsql/grammar/TSqlLexer.interp
pytsql/grammar/TSqlLexer.py
pytsql/grammar/TSqlLexer.tokens
pytsql/grammar/TSqlParser.g4
pytsql/grammar/TSqlParser.interp
pytsql/grammar/TSqlParser.py
pytsql/grammar/TSqlParser.tokens
pytsql/grammar/TSqlParserListener.py
pytsql/grammar/__init__.py
pytsql/grammar/adjust_antlrs_grammar.py
pytsql/grammar/helper_generate_grammar_targets.sh
pytsql/grammar/sa_tsql.py
pytsql/grammar/sa_tsql_cpp_parser.cp311-win_amd64.pyd
pytsql/grammar/cpp_src/TSqlLexer.cpp
pytsql/grammar/cpp_src/TSqlLexer.h
pytsql/grammar/cpp_src/TSqlLexer.interp
pytsql/grammar/cpp_src/TSqlLexer.tokens
pytsql/grammar/cpp_src/TSqlParser.cpp
pytsql/grammar/cpp_src/TSqlParser.h
pytsql/grammar/cpp_src/TSqlParser.interp
pytsql/grammar/cpp_src/TSqlParser.tokens
pytsql/grammar/cpp_src/TSqlParserBaseVisitor.cpp
pytsql/grammar/cpp_src/TSqlParserBaseVisitor.h
pytsql/grammar/cpp_src/TSqlParserVisitor.cpp
pytsql/grammar/cpp_src/TSqlParserVisitor.h
pytsql/grammar/cpp_src/sa_tsql_cpp_parser.cpp
pytsql/grammar/cpp_src/sa_tsql_translator.cpp
pytsql/grammar/cpp_src/sa_tsql_translator.h
pytsql/grammar/cpp_src/speedy_antlr.cpp
pytsql/grammar/cpp_src/speedy_antlr.h
pytsql/grammar/cpp_src/antlr4-cpp-runtime/ANTLRErrorListener.cpp
pytsql/grammar/cpp_src/antlr4-cpp-runtime/ANTLRErrorListener.h
pytsql/grammar/cpp_src/antlr4-cpp-runtime/ANTLRErrorStrategy.cpp
pytsql/grammar/cpp_src/antlr4-cpp-runtime/ANTLRErrorStrategy.h
pytsql/grammar/cpp_src/antlr4-cpp-runtime/ANTLRFileStream.cpp
pytsql/grammar/cpp_src/antlr4-cpp-runtime/ANTLRFileStream.h
pytsql/grammar/cpp_src/antlr4-cpp-runtime/ANTLRInputStream.cpp
pytsql/grammar/cpp_src/antlr4-cpp-runtime/ANTLRInputStream.h
pytsql/grammar/cpp_src/antlr4-cpp-runtime/BailErrorStrategy.cpp
pytsql/grammar/cpp_src/antlr4-cpp-runtime/BailErrorStrategy.h
pytsql/grammar/cpp_src/antlr4-cpp-runtime/BaseErrorListener.cpp
pytsql/grammar/cpp_src/antlr4-cpp-runtime/BaseErrorListener.h
pytsql-1.5.2.dist-info/licenses/LICENSE
pytsql-1.5.2.dist-info/licenses/NOTICE.txt
pytsql-1.5.2.dist-info/METADATA
pytsql-1.5.2.dist-info/WHEEL
pytsql-1.5.2.dist-info/top_level.txt
pytsql-1.5.2.dist-info/RECORD
