Metadata-Version: 2.4
Name: pytsql
Version: 1.5.2
Summary: `Pytsql` allows to run mssql sripts, typically run via GUIs, via CLI.
Author-email: Alex Gonopolskiy <agonopol@gmail.com>, Kevin Klein <kevin.klein@quantco.com>, Encho Mishinev <encho.mishinev@gmail.com>, Sven Giegerich <sven.giegerich@quantco.com>
Maintainer-email: Kevin Klein <kevin.klein@quantco.com>
Project-URL: Source, https://github.com/quantco/pytsql
Keywords: sql,mssql,databases,automation,parametrization
Classifier: Development Status :: 5 - Production/Stable
Classifier: License :: OSI Approved :: BSD License
Classifier: Operating System :: OS Independent
Classifier: Programming Language :: Python :: 3
Classifier: Programming Language :: Python :: 3.9
Classifier: Programming Language :: Python :: 3.10
Classifier: Programming Language :: Python :: 3.11
Classifier: Programming Language :: Python :: 3.12
Classifier: Programming Language :: Python :: 3.13
Classifier: Topic :: Database
Requires-Python: >=3.9
License-File: LICENSE
License-File: NOTICE.txt
Requires-Dist: sqlalchemy<3,>=1.4
Requires-Dist: antlr4-python3-runtime<4.14,>=4.10
Requires-Dist: pyodbc>=4.0.30
Requires-Dist: click
Dynamic: license-file
